urllib3_mock.py
urllib3_mock-0.3.3.dist-info/RECORD
urllib3_mock-0.3.3.dist-info/WHEEL
urllib3_mock-0.3.3.dist-info/pydist.json
urllib3_mock-0.3.3.dist-info/DESCRIPTION.rst
urllib3_mock-0.3.3.dist-info/METADATA
urllib3_mock-0.3.3.dist-info/top_level.txt
