Metadata-Version: 2.0
Name: urllib3-mock
Version: 0.3.3
Summary: A utility library for mocking out the `urllib3` Python library.
Home-page: https://github.com/florentx/urllib3-mock
Author: Florent Xicluna
Author-email: florent.xicluna@gmail.com
License: Apache 2.0
Platform: UNKNOWN
Classifier: Intended Audience :: Developers
Classifier: Intended Audience :: System Administrators
Classifier: Operating System :: OS Independent
Classifier: Topic :: Software Development
Classifier: Programming Language :: Python :: 2
Classifier: Programming Language :: Python :: 3
Provides-Extra: tests
Requires-Dist: pytest; extra == 'tests'
Requires-Dist: pytest-cov; extra == 'tests'
Requires-Dist: flake8; extra == 'tests'
Requires-Dist: requests; extra == 'tests'
